{
  "indexes": [
    {
      "collectionGroup": "attendees",
      "queryScope": "COLLECTION_GROUP",
      "fields": [
        { "fieldPath": "uid", "order": "ASCENDING" },
        { "fieldPath": "status", "order": "ASCENDING" }
      ]
    },
    {
      "collectionGroup": "events",
      "queryScope": "COLLECTION",
      "fields": [
        { "fieldPath": "status", "order": "ASCENDING" },
        { "fieldPath": "city", "order": "ASCENDING" },
        { "fieldPath": "date", "order": "ASCENDING" }
      ]
    },
    {
      "collectionGroup": "events",
      "queryScope": "COLLECTION",
      "fields": [
        { "fieldPath": "status", "order": "ASCENDING" },
        { "fieldPath": "communityId", "order": "ASCENDING" },
        { "fieldPath": "date", "order": "ASCENDING" }
      ]
    },
    {
      "collectionGroup": "communities",
      "queryScope": "COLLECTION",
      "fields": [
        { "fieldPath": "city", "order": "ASCENDING" },
        { "fieldPath": "createdAt", "order": "DESCENDING" }
      ]
    }
  ],
  "fieldOverrides": [
    {
      "collectionGroup": "fcmTokens",
      "fieldPath": "token",
      "indexes": [
        { "order": "ASCENDING", "queryScope": "COLLECTION_GROUP" }
      ]
    },
    {
      "collectionGroup": "members",
      "fieldPath": "uid",
      "indexes": [
        { "order": "ASCENDING", "queryScope": "COLLECTION_GROUP" }
      ]
    }
  ]
}
